ka9q/__init__.py
ka9q/addressing.py
ka9q/control.py
ka9q/discovery.py
ka9q/exceptions.py
ka9q/managed_stream.py
ka9q/monitor.py
ka9q/resequencer.py
ka9q/rtp_recorder.py
ka9q/stream.py
ka9q/stream_quality.py
ka9q/types.py
ka9q/utils.py
ka9q_python-3.3.0.dist-info/licenses/LICENSE
ka9q_python-3.3.0.dist-info/METADATA
ka9q_python-3.3.0.dist-info/WHEEL
ka9q_python-3.3.0.dist-info/top_level.txt
ka9q_python-3.3.0.dist-info/RECORD
