Metadata-Version: 2.4
Name: ka9q-python
Version: 3.3.0
Summary: Python interface for ka9q-radio control and monitoring
Home-page: https://github.com/mijahauan/ka9q-python
Author: Michael Hauan AC0G
Author-email: Michael Hauan AC0G <ac0g@hauan.org>
License: MIT
Project-URL: Homepage, https://github.com/mijahauan/ka9q-python
Project-URL: Documentation, https://github.com/mijahauan/ka9q-python/blob/main/README.md
Project-URL: Repository, https://github.com/mijahauan/ka9q-python
Project-URL: Issues, https://github.com/mijahauan/ka9q-python/issues
Keywords: ka9q-radio,sdr,ham-radio,radio-control
Classifier: Development Status :: 4 - Beta
Classifier: Intended Audience :: Science/Research
Classifier: Intended Audience :: Telecommunications Industry
Classifier: Programming Language :: Python :: 3
Classifier: Programming Language :: Python :: 3.9
Classifier: Programming Language :: Python :: 3.10
Classifier: Programming Language :: Python :: 3.11
Classifier: Programming Language :: Python :: 3.12
Classifier: Topic :: Communications :: Ham Radio
Classifier: Topic :: Scientific/Engineering
Requires-Python: >=3.9
License-File: LICENSE
Requires-Dist: numpy>=1.24.0
Provides-Extra: dev
Requires-Dist: pytest>=7.0.0; extra == "dev"
Requires-Dist: pytest-cov>=4.0.0; extra == "dev"
Dynamic: author
Dynamic: home-page
Dynamic: license-file
Dynamic: requires-python
